ninjaconnect-2.1.45.data/scripts/ninja
wgexpection/Devicelist.py
wgexpection/__init__.py
wgexpection/wireguardexpections.py
wglib/__init__.py
wglib/auth.py
wglib/flavourfinder.py
wglib/headlessdevice.py
wglib/storesess.py
wglib/wg.py
wglib/windowswg.py
wglib/wizard.py
ninjaconnect-2.1.45.dist-info/METADATA
ninjaconnect-2.1.45.dist-info/WHEEL
ninjaconnect-2.1.45.dist-info/top_level.txt
ninjaconnect-2.1.45.dist-info/RECORD
