Metadata-Version: 2.1
Name: ninjaconnect
Version: 2.1.45
Summary: NINJA CONNECT: Your Hassle-Free Device Configuration and Management Wizard!
Home-page: https://pypi.org/project/ninjaconnect/
Author: Prasaanth
Author-email: prasaanth2k@gmail.com
Maintainer: Prasaanth
Classifier: Development Status :: 3 - Alpha
Classifier: License :: OSI Approved :: MIT License
Classifier: Environment :: Console
Classifier: Intended Audience :: Developers
Classifier: Natural Language :: English
Classifier: Programming Language :: Python :: 3
Classifier: Programming Language :: Python :: 3.7
Classifier: Programming Language :: Python :: 3.8
Classifier: Programming Language :: Python :: 3.9
Classifier: Programming Language :: Python :: 3.10
Classifier: Programming Language :: Python :: 3.11
Classifier: Programming Language :: Python :: 3.12
Classifier: Programming Language :: Python :: 3 :: Only
Classifier: Operating System :: OS Independent
Requires-Dist: keyring ==23.5.0
Requires-Dist: readchar ==4.0.5
Requires-Dist: Requests ==2.31.0
Requires-Dist: rich ==13.6.0
Requires-Dist: setuptools ==68.2.2
